.coveragerc
.gitignore
CHANGELOG.rst
MANIFEST.in
README.rst
setup.cfg
setup.py
.github/workflows/main.yml
author/__init__.py
author/backends.py
author/decorators.py
author/middlewares.py
author/recivers.py
author/locale/cs_CZ/LC_MESSAGES/django.po
author/locale/pt_BR/LC_MESSAGES/django.po
django_author.egg-info/PKG-INFO
django_author.egg-info/SOURCES.txt
django_author.egg-info/dependency_links.txt
django_author.egg-info/requires.txt
django_author.egg-info/top_level.txt
django_author.egg-info/zip-safe