Metadata-Version: 2.1
Name: django-author
Version: 1.1.0
Summary: Add special User ForeignKey fields which update automatically
Home-page: https://github.com/lambdalisue/django-author
Download-URL: https://github.com/lambdalisue/django-author/tarball/master
Author: Alisue
Author-email: lambdalisue@hashnote.net
License: MIT
Keywords: django author object universal
Platform: UNKNOWN
Classifier: Framework :: Django
Classifier: Intended Audience :: Developers
Classifier: License :: OSI Approved :: MIT License
Classifier: Programming Language :: Python
Classifier: Topic :: Internet :: WWW/HTTP
